setup.cfg
setup.py
tow/__init__.py
tow/attrs.py
tow/dockerfile.py
tow/main.py
tow/modules.py
tow/version.py
tow.egg-info/PKG-INFO
tow.egg-info/SOURCES.txt
tow.egg-info/dependency_links.txt
tow.egg-info/entry_points.txt
tow.egg-info/pbr.json
tow.egg-info/requires.txt
tow.egg-info/top_level.txt
tow/commands/__init__.py
tow/commands/build.py
tow/commands/command.py
tow/commands/create.py
tow/commands/process.py
tow/commands/run.py
tow/commands/utils.py
tow/templates/Dockerfile.tmpl
tow/templates/__init__.py
tow/templates/default.py.tmpl
tow/templates/mapping.py.tmpl
tow/templates/mapping.sh.tmpl
tow/templates/tow.sh.tmpl