Metadata-Version: 1.1
Name: tow
Version: 1.0.0a7
Summary: Tow is tool for automatization docker configuration managment workflow
Home-page: https://github.com/alekseiko/tow
Author: Aleksei Kornev, Nikolay Yurin
Author-email: aleksei.kornev@gmail.com, 
License: UNKNOWN
Platform: UNKNOWN
Classifier: Environment :: Console
Classifier: Intended Audience :: Developers
Classifier: Intended Audience :: System Administrators
Classifier: Operating System :: Unix
Classifier: Operating System :: POSIX
Classifier: Programming Language :: Python
Classifier: Programming Language :: Python :: 2.7
Classifier: Topic :: Software Development
Classifier: Topic :: Software Development :: Build Tools
Classifier: Topic :: System :: Clustering
Classifier: Topic :: System :: Software Distribution
Classifier: Topic :: System :: Systems Administration
